{
    "wpid": "WP5148",
    "organisms": ["Homo sapiens"],
    "description": "Hypothetical pathway for complement-mediated inflammation of the pulmonary alveolus in COVID-19. AEC\u2010II=Type II alveolar epithelial cell, EC=endothelial cells and MC=monocytes.",
    "ontology-ids": [
        "DOID:0080600",
        "PW:0000504",
        "CL:0010003"
    ],
    "last-edited": "2024-01-31",
    "title": "Complement-mediated inflammation of pulmonary alveolus in COVID-19 (hypothetical pathway)",
    "authors": [
        "Susan",
        "Eweitz",
        "Egonw",
        "NhungP",
        "Mkutmon"
    ],
    "revision": "r128306"
}