{
    "wpid": "WP133",
    "organisms": ["Rattus norvegicus"],
    "description": "Dodecanoate, or lauric acid, is found in the fats and oils of both plants and animals, especially coconut and palm kernel oil. This pathway shows the degradation of dodecanoate leading to beta oxidation.",
    "ontology-ids": [
        "PW:0000642",
        "PW:0001253"
    ],
    "last-edited": "2025-11-16",
    "title": "Fatty acid omega-oxidation",
    "authors": [
        "Evelo",
        "MaintBot",
        "Thomas",
        "Cizar",
        "Christine Chichester",
        "Youssefwalid",
        "Eweitz",
        "Egonw",
        "DeSl"
    ],
    "revision": "r141463"
}