{
    "wpid": "WP5576",
    "organisms": ["Homo sapiens"],
    "description": "The relationship between killer cell immunoglobulin-like receptors (KIRs) on natural killer (NK) cells and human leukocyte antigen C (HLA-C) molecules on trophoblast cells during pregnancy.",
    "ontology-ids": [
        "CL:0000623",
        "PW:0000003"
    ],
    "last-edited": "2025-08-18",
    "title": "Killer cell immunoglobulin-like receptors and human leukocyte antigen C pathway",
    "authors": [
        "Johidi2",
        "AlexanderPico",
        "Egonw"
    ],
    "revision": "r140397"
}