{
    "wpid": "WP5078",
    "organisms": ["Homo sapiens"],
    "description": "T cells are important effector cells in pancreatic cancer. Their function is inhibited by various cellular interactions and secreted factors in the tumor microenvironment (TME). Both immune cells and pancreatic cancer cells are able to modulate T cell activation.",
    "ontology-ids": [
        "DOID:1793",
        "CL:0002410",
        "CL:0000145",
        "CL:0001064",
        "CL:0000889",
        "PW:0000023",
        "PW:0000626",
        "CL:0000084",
        "CL:0000625",
        "PW:0000013"
    ],
    "last-edited": "2024-02-18",
    "title": "T cell modulation in pancreatic cancer",
    "authors": [
        "DanaMustafa",
        "Mkutmon",
        "Eweitz",
        "IsabelWassink"
    ],
    "revision": "r128646"
}