{
    "wpid": "WP4336",
    "organisms": ["Homo sapiens"],
    "description": "This pathway is based on the [[Pathway:WP428 | Wnt signaling pathway]] with information on lncRNA involvement in hepatocellular carcinoma from Fig 3 in Klingenberg et al. Phosphorylation sites were added based on information from PhosphoSitePlus (R), www.phosphosite.org.",
    "ontology-ids": [
        "PW:0000598",
        "PW:0000201",
        "PW:0000008",
        "DOID:684",
        "PW:0000605",
        "CL:0000182",
        "CL:0000034"
    ],
    "last-edited": "2024-07-28",
    "title": "ncRNAs in Wnt signaling in hepatocellular carcinoma",
    "authors": [
        "Khanspers",
        "Fehrhart",
        "Egonw",
        "Eweitz"
    ],
    "revision": "r134815"
}