{
    "wpid": "WP2003",
    "organisms": ["Homo sapiens"],
    "description": "This cataloge pathway was created using the database from \"http://diana.cslab.ece.ntua.gr/tarbase/\" with exclusions based on evidance type. This pathway only incldes miR targeted genes expressed in Leukocyte cells. This pathway is meant for data mapping.",
    "ontology-ids": [
        "PW:0000808",
        "CL:0000738"
    ],
    "last-edited": "2024-10-28",
    "title": "miR-targeted genes in leukocytes",
    "authors": [
        "Samuel Sklar",
        "MaintBot",
        "MartijnVanIersel",
        "Khanspers",
        "Zari",
        "Lindarieswijk",
        "Mkutmon",
        "Eweitz"
    ],
    "revision": "r135699"
}