{
    "wpid": "WP3189",
    "organisms": ["Bos taurus"],
    "description": "CYP metabolism of felbamate, with the metabolites 2-hydroxyfelbamate, p-hydroxyfelbamate, and 3-Hydroxy-2-phenylpropylcarbamate. The last further metabolizes to 3-carbamoyl-2-phenylpropionaldehyde, atropaldehyde, and 3-carbamoyl-2-phenylpropionic acid.",
    "ontology-ids": ["PW:0000923"],
    "last-edited": "2026-02-17",
    "title": "Felbamate metabolism",
    "authors": [
        "Mkutmon",
        "MaintBot",
        "Eweitz",
        "Egonw"
    ],
    "revision": "r142450"
}